AUTHORS.rst
LICENSE
MANIFEST.in
README.rst
buildout.cfg
pyproject.toml
requirements.txt
setup.py
version.txt
beat/__init__.py
beat.backend.python.egg-info/PKG-INFO
beat.backend.python.egg-info/SOURCES.txt
beat.backend.python.egg-info/dependency_links.txt
beat.backend.python.egg-info/entry_points.txt
beat.backend.python.egg-info/not-zip-safe
beat.backend.python.egg-info/requires.txt
beat.backend.python.egg-info/top_level.txt
beat/backend/__init__.py
beat/backend/python/__init__.py
beat/backend/python/algorithm.py
beat/backend/python/baseformat.py
beat/backend/python/data.py
beat/backend/python/data_loaders.py
beat/backend/python/database.py
beat/backend/python/dataformat.py
beat/backend/python/exceptions.py
beat/backend/python/hash.py
beat/backend/python/helpers.py
beat/backend/python/inputs.py
beat/backend/python/library.py
beat/backend/python/loader.py
beat/backend/python/outputs.py
beat/backend/python/protocoltemplate.py
beat/backend/python/stats.py
beat/backend/python/utils.py
beat/backend/python/execution/__init__.py
beat/backend/python/execution/algorithm.py
beat/backend/python/execution/database.py
beat/backend/python/execution/helpers.py
beat/backend/python/execution/loop.py
beat/backend/python/execution/messagehandlers.py
beat/backend/python/scripts/__init__.py
beat/backend/python/scripts/databases_provider.py
beat/backend/python/scripts/describe.py
beat/backend/python/scripts/execute.py
beat/backend/python/scripts/index.py
beat/backend/python/scripts/loop_execute.py
beat/backend/python/test/__init__.py
beat/backend/python/test/mocks.py
beat/backend/python/test/test_algorithm.py
beat/backend/python/test/test_data.py
beat/backend/python/test/test_data_loaders.py
beat/backend/python/test/test_database.py
beat/backend/python/test/test_database_view.py
beat/backend/python/test/test_databases_index.py
beat/backend/python/test/test_databases_provider.py
beat/backend/python/test/test_dbexecutor.py
beat/backend/python/test/test_executor.py
beat/backend/python/test/test_format_array.py
beat/backend/python/test/test_format_extends.py
beat/backend/python/test/test_format_missing_attributes.py
beat/backend/python/test/test_format_object.py
beat/backend/python/test/test_format_simple.py
beat/backend/python/test/test_format_unsafe_cast.py
