Metadata-Version: 2.1
Name: beat.backend.python
Version: 1.7.15
Summary: Python Backend for the BEAT Platform
Home-page: https://gitlab.idiap.ch/beat/beat.backend.python
Author: Idiap Research Institute
Author-email: beat.support@idiap.ch
License: BSD
Classifier: Framework :: BEAT
Classifier: Development Status :: 5 - Production/Stable
Classifier: Intended Audience :: Developers
Classifier: License :: OSI Approved :: BSD License
Classifier: Natural Language :: English
Classifier: Programming Language :: Python
Classifier: Programming Language :: Python :: 3
Classifier: Topic :: Software Development :: Libraries :: Python Modules
License-File: LICENSE
License-File: AUTHORS.rst
